Workbook

Sheet Transactions
A1: Date | B1: Category | C1: Subcategory | D1: Type | E1: Amount | F1: Payment Method | G1: Notes
A2: 2026-01-01 | B2: =_xlfn.XLOOKUP(C2,Categories!A:A,Categories!B:B) -> Income | C2: Salary | D2: Income | E2: 1200 | F2: Bank Transfer
A3: 2026-01-03 | B3: =_xlfn.XLOOKUP(C3,Categories!A:A,Categories!B:B) -> Food | C3: Groceries | D3: Expense | E3: 45 | F3: Card
A4: 2026-01-05 | B4: =_xlfn.XLOOKUP(C4,Categories!A:A,Categories!B:B) -> Transport | C4: Bus | D4: Expense | E4: 15 | F4: Cash
A5: 2026-01-07 | B5: =_xlfn.XLOOKUP(C5,Categories!A:A,Categories!B:B) -> Entertainment | C5: Movies | D5: Expense | E5: 20 | F5: Card
A6: 2026-01-10 | B6: =_xlfn.XLOOKUP(C6,Categories!A:A,Categories!B:B) -> Food | C6: Restaurant | D6: Expense | E6: 30 | F6: Card
A7: 2026-01-12 | B7: =_xlfn.XLOOKUP(C7,Categories!A:A,Categories!B:B) -> Income | C7: Freelance | D7: Income | E7: 300 | F7: Bank Transfer
A8: 46037 | B8: =_xlfn.XLOOKUP(C8,Categories!A:A,Categories!B:B) -> Food | C8: Groceries | D8: Expense | E8: 52 | F8: Card
A9: 46038 | B9: =_xlfn.XLOOKUP(C9,Categories!A:A,Categories!B:B) -> Transport | C9: Metro | D9: Expense | E9: 18 | F9: Card
A10: 46039 | B10: =_xlfn.XLOOKUP(C10,Categories!A:A,Categories!B:B) -> Food | C10: Restaurant | D10: Expense | E10: 27 | F10: Card
A11: 46040 | B11: =_xlfn.XLOOKUP(C11,Categories!A:A,Categories!B:B) -> Entertainment | C11: Streaming | D11: Expense | E11: 12 | F11: Card | G11: Netflix
A12: 46042 | B12: =_xlfn.XLOOKUP(C12,Categories!A:A,Categories!B:B) -> Income | C12: Freelance | D12: Income | E12: 250 | F12: Bank Transfer
A13: 46043 | B13: =_xlfn.XLOOKUP(C13,Categories!A:A,Categories!B:B) -> Utilities | C13: Electricity | D13: Expense | E13: 60 | F13: Bank Transfer
A14: 46044 | B14: =_xlfn.XLOOKUP(C14,Categories!A:A,Categories!B:B) -> Food | C14: Groceries | D14: Expense | E14: 48 | F14: Cash
A15: 46045 | B15: =_xlfn.XLOOKUP(C15,Categories!A:A,Categories!B:B) -> Transport | C15: Uber | D15: Expense | E15: 22 | F15: Card
A16: 46046 | B16: =_xlfn.XLOOKUP(C16,Categories!A:A,Categories!B:B) -> Entertainment | C16: Gaming | D16: Expense | E16: 35 | F16: Card
A17: 46047 | B17: =_xlfn.XLOOKUP(C17,Categories!A:A,Categories!B:B) -> Health | C17: Pharmacy | D17: Expense | E17: 15 | F17: Cash
A18: 46049 | B18: =_xlfn.XLOOKUP(C18,Categories!A:A,Categories!B:B) -> Food | C18: Restaurant | D18: Expense | E18: 33 | F18: Card
A19: 46050 | B19: =_xlfn.XLOOKUP(C19,Categories!A:A,Categories!B:B) -> Utilities | C19: Internet | D19: Expense | E19: 40 | F19: Bank Transfer
A20: 46052 | B20: =_xlfn.XLOOKUP(C20,Categories!A:A,Categories!B:B) -> Income | C20: Salary | D20: Income | E20: 1200 | F20: Bank Transfer
A21: 46054 | B21: =_xlfn.XLOOKUP(C21,Categories!A:A,Categories!B:B) -> Food | C21: Groceries | D21: Expense | E21: 55 | F21: Card
A22: 46055 | B22: =_xlfn.XLOOKUP(C22,Categories!A:A,Categories!B:B) -> Transport | C22: Bus | D22: Expense | E22: 10 | F22: Cash
A23: 46056 | B23: =_xlfn.XLOOKUP(C23,Categories!A:A,Categories!B:B) -> Entertainment | C23: Movies | D23: Expense | E23: 25 | F23: Card
... A31: 46066 | B31: =_xlfn.XLOOKUP(C31,Categories!A:A,Categories!B:B) -> Shopping | C31: Clothes | D31: Expense | E31: 120 | F31: Card
A32: 46067 | B32: =_xlfn.XLOOKUP(C32,Categories!A:A,Categories!B:B) -> Food | C32: Restaurant | D32: Expense | E32: 45 | F32: Card | G32: Valentine's
A33: 46069 | B33: =_xlfn.XLOOKUP(C33,Categories!A:A,Categories!B:B) -> Transport | C33: Metro | D33: Expense | E33: 18 | F33: Card
A34: 46070 | B34: =_xlfn.XLOOKUP(C34,Categories!A:A,Categories!B:B) -> Utilities | C34: Electricity | D34: Expense | E34: 70 | F34: Bank Transfer
A35: 46071 | B35: =_xlfn.XLOOKUP(C35,Categories!A:A,Categories!B:B) -> Health | C35: Doctor | D35: Expense | E35: 50 | F35: Cash
A36: 46073 | B36: =_xlfn.XLOOKUP(C36,Categories!A:A,Categories!B:B) -> Food | C36: Groceries | D36: Expense | E36: 49 | F36: Card
A37: 46074 | B37: =_xlfn.XLOOKUP(C37,Categories!A:A,Categories!B:B) -> Entertainment | C37: Gaming | D37: Expense | E37: 30 | F37: Card
A38: 46075 | B38: =_xlfn.XLOOKUP(C38,Categories!A:A,Categories!B:B) -> Transport | C38: Bus | D38: Expense | E38: 12 | F38: Cash
A39: 46076 | B39: =_xlfn.XLOOKUP(C39,Categories!A:A,Categories!B:B) -> Income | C39: Salary | D39: Income | E39: 1200 | F39: Bank Transfer
A40: 46077 | B40: =_xlfn.XLOOKUP(C40,Categories!A:A,Categories!B:B) -> Shopping | C40: Electronics | D40: Expense | E40: 200 | F40: Card
A41: 46078 | B41: =_xlfn.XLOOKUP(C41,Categories!A:A,Categories!B:B) -> Food | C41: Restaurant | D41: Expense | E41: 36 | F41: Card
A42: 46079 | B42: =_xlfn.XLOOKUP(C42,Categories!A:A,Categories!B:B) -> Utilities | C42: Internet | D42: Expense | E42: 42 | F42: Bank Transfer
A43: 46080 | B43: =_xlfn.XLOOKUP(C43,Categories!A:A,Categories!B:B) -> Health | C43: Gym | D43: Expense | E43: 45 | F43: Bank Transfer
A44: 46082 | B44: =_xlfn.XLOOKUP(C44,Categories!A:A,Categories!B:B) -> Food | C44: Groceries | D44: Expense | E44: 58 | F44: Card
... A57: 46095 | B57: =_xlfn.XLOOKUP(C57,Categories!A:A,Categories!B:B) -> Food | C57: Restaurant | D57: Expense | E57: 42 | F57: Card

Sheet Categories
A1: Subcategory | B1: Category
A2: Groceries | B2: Food
A3: Restaurant | B3: Food
A4: Streaming | B4: Entertainment
A5: Movies | B5: Entertainment
A6: Gaming | B6: Entertainment
A7: Concert | B7: Entertainment
A8: Bus | B8: Transport
A9: Metro | B9: Transport
A10: Uber | B10: Transport
A11: Salary | B11: Income
A12: Freelance | B12: Income
... A21: Accessories | B21: Shopping

Sheet Summary
A1: Total Income | B1: =SUMIF(Transactions!D:D,"Income",Transactions!E:E) -> 5930
A2: Total Expenses | B2: =SUMIF(Transactions!D:D,"Expense",Transactions!E:E) -> 1990
A3: Net Savings | B3: =B1-B2 -> 3940

Sheet Pivot table
A1: Type | B1: Expense
A3: Category | B3: Sum of Amount
A4: Entertainment | B4: 236
A5: Food | B5: 720
A6: Transport | B6: 152
A7: Utilities | B7: 265
A8: Health | B8: 172
A9: Shopping | B9: 445
A10: Grand Total | B10: 1990
